processador_imagem_virtual_da/__init__.py
processador_imagem_virtual_da/processamento/__init__.py
processador_imagem_virtual_da/processamento/combinacao.py
processador_imagem_virtual_da/processamento/transformacao.py
processador_imagem_virtual_da/utilidade/__init__.py
processador_imagem_virtual_da/utilidade/io.py
processador_imagem_virtual_da/utilidade/plot.py
processador_imagem_virtual_da-0.0.3.dist-info/METADATA
processador_imagem_virtual_da-0.0.3.dist-info/WHEEL
processador_imagem_virtual_da-0.0.3.dist-info/top_level.txt
processador_imagem_virtual_da-0.0.3.dist-info/RECORD
