Metadata-Version: 2.1
Name: processador-imagem-virtual-da
Version: 0.0.3
Summary: Pacote de processamento de imagem via Skimage
Home-page: https://github.com/DanielHisatugu/desafio-python-processador-imagem-virtual
Author: Daniel Hisatugu
Author-email: daniel.hisatugu@gmail.com
License: UNKNOWN
Platform: UNKNOWN
Requires-Python: >=3.8
Requires-Dist: matplotlib
Requires-Dist: numpy
Requires-Dist: scikit-image (>=0.16.1)
